[
    {
        "name": "writer",
        "columns": [
            {
                "name": "situation",
                "type": "DATE",
                "references": null
            },
            {
                "name": "weight",
                "type": "TEXT",
                "references": null
            },
            {
                "name": "professional",
                "type": "VARCHAR(50)",
                "references": null
            }
        ],
        "primary_key": "situation",
        "foreign_keys": [
            {
                "column": "situation",
                "references": "section"
            }
        ]
    },
    {
        "name": "section",
        "columns": [
            {
                "name": "after",
                "type": "VARCHAR(50)",
                "references": null
            },
            {
                "name": "institution",
                "type": "DATE",
                "references": null
            }
        ],
        "primary_key": "after",
        "foreign_keys": [
            {
                "column": "after",
                "references": "information"
            }
        ]
    },
    {
        "name": "information",
        "columns": [
            {
                "name": "test",
                "type": "DATE",
                "references": null
            },
            {
                "name": "treat",
                "type": "TEXT",
                "references": null
            },
            {
                "name": "place",
                "type": "VARCHAR(50)",
                "references": null
            }
        ],
        "primary_key": "test",
        "foreign_keys": [
            {
                "column": "test",
                "references": "language"
            }
        ]
    },
    {
        "name": "language",
        "columns": [
            {
                "name": "record",
                "type": "VARCHAR(50)",
                "references": null
            },
            {
                "name": "not",
                "type": "DATE",
                "references": null
            }
        ],
        "primary_key": "record",
        "foreign_keys": [
            {
                "column": "record",
                "references": "price"
            }
        ]
    },
    {
        "name": "price",
        "columns": [
            {
                "name": "available",
                "type": "DATE",
                "references": null
            },
            {
                "name": "less",
                "type": "TEXT",
                "references": null
            },
            {
                "name": "within",
                "type": "VARCHAR(50)",
                "references": null
            }
        ],
        "primary_key": "available",
        "foreign_keys": [
            {
                "column": "available",
                "references": "audience"
            }
        ]
    },
    {
        "name": "audience",
        "columns": [
            {
                "name": "tonight",
                "type": "VARCHAR(50)",
                "references": null
            },
            {
                "name": "including",
                "type": "DATE",
                "references": null
            }
        ],
        "primary_key": "tonight",
        "foreign_keys": [
            {
                "column": "tonight",
                "references": "space"
            }
        ]
    },
    {
        "name": "space",
        "columns": [
            {
                "name": "image",
                "type": "DATE",
                "references": null
            },
            {
                "name": "gun",
                "type": "TEXT",
                "references": null
            },
            {
                "name": "represent",
                "type": "VARCHAR(50)",
                "references": null
            }
        ],
        "primary_key": "image",
        "foreign_keys": [
            {
                "column": "image",
                "references": "dinner"
            }
        ]
    },
    {
        "name": "dinner",
        "columns": [
            {
                "name": "account",
                "type": "VARCHAR(50)",
                "references": null
            },
            {
                "name": "member",
                "type": "DATE",
                "references": null
            }
        ],
        "primary_key": "account",
        "foreign_keys": [
            {
                "column": "account",
                "references": "serious"
            }
        ]
    },
    {
        "name": "serious",
        "columns": [
            {
                "name": "several",
                "type": "DATE",
                "references": null
            },
            {
                "name": "upon",
                "type": "TEXT",
                "references": null
            },
            {
                "name": "page",
                "type": "VARCHAR(50)",
                "references": null
            }
        ],
        "primary_key": "several",
        "foreign_keys": [
            {
                "column": "several",
                "references": "place"
            }
        ]
    },
    {
        "name": "place",
        "columns": [
            {
                "name": "knowledge",
                "type": "VARCHAR(50)",
                "references": null
            },
            {
                "name": "own",
                "type": "DATE",
                "references": null
            }
        ],
        "primary_key": "knowledge",
        "foreign_keys": [
            {
                "column": "knowledge",
                "references": "degree"
            }
        ]
    },
    {
        "name": "degree",
        "columns": [
            {
                "name": "training",
                "type": "DATE",
                "references": null
            },
            {
                "name": "industry",
                "type": "TEXT",
                "references": null
            },
            {
                "name": "eye",
                "type": "VARCHAR(50)",
                "references": null
            }
        ],
        "primary_key": "training",
        "foreign_keys": [
            {
                "column": "training",
                "references": "writer"
            }
        ]
    }
]