[
    {
        "name": "hard",
        "columns": [
            {
                "name": "site",
                "type": "DATE",
                "references": null
            },
            {
                "name": "resource",
                "type": "TEXT",
                "references": null
            },
            {
                "name": "wind",
                "type": "VARCHAR(50)",
                "references": null
            }
        ],
        "primary_key": "site",
        "foreign_keys": [
            {
                "column": "site",
                "references": "church"
            }
        ]
    },
    {
        "name": "church",
        "columns": [
            {
                "name": "least",
                "type": "VARCHAR(50)",
                "references": null
            },
            {
                "name": "give",
                "type": "DATE",
                "references": null
            }
        ],
        "primary_key": "least",
        "foreign_keys": [
            {
                "column": "least",
                "references": "just"
            }
        ]
    },
    {
        "name": "just",
        "columns": [
            {
                "name": "whom",
                "type": "DATE",
                "references": null
            },
            {
                "name": "so",
                "type": "TEXT",
                "references": null
            },
            {
                "name": "executive",
                "type": "VARCHAR(50)",
                "references": null
            }
        ],
        "primary_key": "whom",
        "foreign_keys": [
            {
                "column": "whom",
                "references": "leader"
            }
        ]
    },
    {
        "name": "leader",
        "columns": [
            {
                "name": "somebody",
                "type": "VARCHAR(50)",
                "references": null
            },
            {
                "name": "ball",
                "type": "DATE",
                "references": null
            }
        ],
        "primary_key": "somebody",
        "foreign_keys": [
            {
                "column": "somebody",
                "references": "fine"
            }
        ]
    },
    {
        "name": "fine",
        "columns": [
            {
                "name": "all",
                "type": "DATE",
                "references": null
            },
            {
                "name": "break",
                "type": "TEXT",
                "references": null
            },
            {
                "name": "appear",
                "type": "VARCHAR(50)",
                "references": null
            }
        ],
        "primary_key": "all",
        "foreign_keys": [
            {
                "column": "all",
                "references": "feel"
            }
        ]
    },
    {
        "name": "feel",
        "columns": [
            {
                "name": "finally",
                "type": "VARCHAR(50)",
                "references": null
            },
            {
                "name": "property",
                "type": "DATE",
                "references": null
            }
        ],
        "primary_key": "finally",
        "foreign_keys": [
            {
                "column": "finally",
                "references": "staff"
            }
        ]
    },
    {
        "name": "staff",
        "columns": [
            {
                "name": "table",
                "type": "DATE",
                "references": null
            },
            {
                "name": "century",
                "type": "TEXT",
                "references": null
            },
            {
                "name": "successful",
                "type": "VARCHAR(50)",
                "references": null
            }
        ],
        "primary_key": "table",
        "foreign_keys": [
            {
                "column": "table",
                "references": "recent"
            }
        ]
    },
    {
        "name": "recent",
        "columns": [
            {
                "name": "leave",
                "type": "VARCHAR(50)",
                "references": null
            },
            {
                "name": "TV",
                "type": "DATE",
                "references": null
            }
        ],
        "primary_key": "leave",
        "foreign_keys": [
            {
                "column": "leave",
                "references": "hard"
            }
        ]
    }
]